artificer/__init__.py
artificer/objects/__init__.py
artificer/objects/base.py
artificer/objects/features.py
artificer_objects-0.1.0a3.dist-info/METADATA
artificer_objects-0.1.0a3.dist-info/WHEEL
artificer_objects-0.1.0a3.dist-info/licenses/LICENSE
artificer_objects-0.1.0a3.dist-info/RECORD
