Metadata-Version: 2.4
Name: artificer-objects
Version: 0.1.0a3
Summary: Object store exposed to agents as MCP server
License-Expression: MIT
License-File: LICENSE
Keywords: agents,mcp,object-store
Classifier: Development Status :: 3 - Alpha
Classifier: Intended Audience :: Developers
Classifier: License :: OSI Approved :: MIT License
Classifier: Programming Language :: Python :: 3
Classifier: Programming Language :: Python :: 3.13
Requires-Python: >=3.13
Requires-Dist: artificer-cli
Requires-Dist: pydantic>=2.0
Requires-Dist: questionary>=2.0
